Workbook

Sheet Cover
B3: BNP PARIBAS — ALM MASTER MODEL
B4: Asset-Liability Management | Full-Cycle ALM Engine
B5: Calibrated to Q4 2025 Actuals | Basel III / CRR2 / EBA/GL/2022/14
B7: MODEL OVERVIEW
B8: Institution | C8: =Engine!C108 -> BNP Paribas SA
B9: Reporting Currency | C9: =Engine!C106&" — "&Engine!C107 -> EUR — EUR millions
B10: Base Year | C10: =Engine!C105 -> 2025A
B11: Forecast Horizon | C11: =Engine!C110 -> 3 Years (2026F–2028F)
B12: Regulatory Framework | C12: =Engine!C109 -> EU — Basel III / CRR2 / Del. Reg. (EU) 2022/786
B13: Scenarios | C13: Base | Rate Hike | Rate Cut | Stress
B14: Model Version | C14: =Engine!C103 -> v1.0
B16: ARCHITECTURE
B17: Sheet | C17: Role
B18: Dashboard | C18: Executive ALCO view — scenario selector, KPI cards, NII waterfall, EVE sensitivity
B19: Engine | C19: Central control layer — rate curve, scenario inputs, CHOOSE-based propagation
B20: Model | C20: Full analytical engine — 15 modular sections, 1,000+ formulas
B21: Master Balance Sheet | C21: Source-of-truth balance sheet — actuals + three forecast years
B23: KEY METRICS SNAPSHOT (Base Scenario — 2026F)
B24: NII (€bn) | C24: NIM | D24: CET1 | E24: LCR | F24: NSFR | G24: EVE/Tier 1
B25: =Dashboard!B8 -> 22.685669 | C25: =Dashboard!C8 -> 0.017379544 | D25: =Dashboard!D8 -> 0.15879656 | E25: =Dashboard!E8 -> 1.5354828 | F25: =Dashboard!F8 -> 1.0284199 | G25: =Dashboard!G8 -> 0.13246837
B27: AUTHOR
B28: Name | C28: =Engine!F111 -> Hossam Eltarrass
B29: Role | C29: ALM & Treasury Risk Analyst
B30: LinkedIn | C30: linkedin.com/in/hossameltarrass
B31: GitHub | C31: github.com/hossam-eltarrass
B32: Last Updated | C32: =TEXT(Engine!C111,"DD MMMM YYYY") -> 24 March 2026
B34: DATA SOURCE & DISCLAIMER
B35: Balance sheet actuals sourced from BNP Paribas Q4 2025 Results Press Release (verified public disclosure). All actuals are clearly labeled; forecast years are model-generated.
B36: Model built to bank-level standard for portfolio purposes. All regulatory references are to publicly available EBA guidelines and EU regulations.
B38: ="Model "&Engine!C103&" | Last updated: "&TEXT(Engine!C111,"DD-MMM-YYYY")&" | Prepared by: "&Engine!F111 -> Model v1.0 | Last updated: 24-Mar-2026 | Prepared by: Hossam Eltarrass

Sheet Dashboard
B2: BNP PARIBAS — ALM MASTER MODEL | G2: ▸ ACTIVE SCENARIO
B3: =Engine!C108&" | "&Engine!C106&" | Scenario: "&CHOOSE(Engine!C4,"Base","Rate Hike","Rate Cut","Stress")&" | Base year: "&Engine!C105 -> BNP Paribas SA | EUR | Scenario: Base | Base year: 2025A | G3: Base
B4: Forecast: 2026F–2028F | Basel III / CRR2 / Del. Reg. (EU) 2022/786 / EBA/GL/2022/14 | G4: =MATCH(G3,{"Base","Rate Hike","Rate Cut","Stress"},0) -> 1
B6: ="KEY METRICS — 2026F vs 2025A | "&CHOOSE(Dashboard!G4,"Base","Rate Hike","Rate Cut","Stress") -> KEY METRICS — 2026F vs 2025A | Base
B7: NII (€bn) | C7: NIM | D7: CET1 Ratio | E7: LCR | F7: NSFR | G7: EVE / Tier 1
B8: =Model!D23/1000 -> 22.685669 | C8: =Model!E132 -> 0.017379544 | D8: =Model!E138 -> 0.15879656 | E8: =Model!E140 -> 1.5354828 | F8: =Model!E141 -> 1.0284199 | G8: =Model!E229 -> 0.13246837
B9: =(Model!D23-Model!C23)/1000 -> 0.6004161 | C9: =Model!E132-Model!D132 -> 6.0649992e-05 | D9: =Model!E138-Model!D138 -> 0.0013406131 | E9: =Model!E140-Model!D140 -> -0.018924085 | F9: =Model!E141-Model!D141 -> -0.070493225 | G9: =IF(Model!E229>0.15,"BREACH","OK") -> OK
D10: min 13.5% | E10: min 100% | F10: min 1.00x | G10: outlier >15%
B12: BALANCE SHEET FORECAST (EUR millions)
C13: 2025A | D13: 2026F | E13: 2027F | F13: 2028F
B14: ASSETS
B15: Cash & CB reserves | C15: =Engine!D126 -> 211330 | D15: =Engine!E126 -> 214325.33 | E15: =Engine!F126 -> 217157.6 | F15: =Engine!G126 -> 219876.42
B16: Trading assets | C16: =Engine!D127 -> 870245 | D16: =Engine!E127 -> 870245 | E16: =Engine!F127 -> 870245 | F16: =Engine!G127 -> 870245
B17: Loans to customers | C17: =Engine!D128 -> 897358 | D17: =Engine!E128 -> 924278.74 | E17: =Engine!F128 -> 952007.1 | F17: =Engine!G128 -> 980567.32
B18: Interbank loans | C18: =Engine!D129 -> 26259 | D18: =Engine!E129 -> 26259 | E18: =Engine!F129 -> 26259 | F18: =Engine!G129 -> 26259
B19: Securities | C19: =Engine!D130 -> 153107 | D19: =Engine!E130 -> 157700.21 | E19: =Engine!F130 -> 162431.22 | F19: =Engine!G130 -> 167304.15
B20: Other assets | C20: =Engine!D131 -> 634682 | D20: =Engine!E131 -> 641028.82 | E20: =Engine!F131 -> 647439.11 | F20: =Engine!G131 -> 653913.5
B21: TOTAL ASSETS | C21: =Engine!D132 -> 2792981 | D21: =Engine!E132 -> 2833837.1 | E21: =Engine!F132 -> 2875539 | F21: =Engine!G132 -> 2918165.4
B23: LIABILITIES & EQUITY
B24: Customer deposits | C24: =Engine!D136 -> 1075564 | D24: =Engine!E136 -> 1102453.1 | E24: =Engine!F136 -> 1130014.4 | F24: =Engine!G136 -> 1158264.8
B25: Interbank funding | C25: =Engine!D137 -> 69938 | D25: =Engine!E137 -> 69938 | E25: =Engine!F137 -> 69938 | F25: =Engine!G137 -> 69938
B26: Repo funding | C26: =Engine!D138 -> 357947 | D26: =Engine!E138 -> 357947 | E26: =Engine!F138 -> 357947 | F26: =Engine!G138 -> 357947
B27: Bonds issued | C27: =Engine!D139 -> 173933 | D27: =Engine!E139 -> 173933 | E27: =Engine!F139 -> 173933 | F27: =Engine!G139 -> 173933
B28: Subordinated debt | C28: =Engine!D140 -> 34468 | D28: =Engine!E140 -> 34468 | E28: =Engine!F140 -> 34468 | F28: =Engine!G140 -> 34468
B29: Other liabilities | C29: =Engine!D141 -> 948958 | D29: =Engine!E141 -> 958447.58 | E29: =Engine!F141 -> 968032.06 | F29: =Engine!G141 -> 977712.38
B30: TOTAL LIABILITIES | C30: =Engine!D142 -> 2660808 | D30: =Engine!E142 -> 2697186.7 | E30: =Engine!F142 -> 2734332.5 | F30: =Engine!G142 -> 2772263.2
B31: Equity | C31: =Engine!D145 -> 132173 | D31: =Engine!E145 -> 136650.42 | E31: =Engine!F145 -> 141206.54 | F31: =Engine!G145 -> 145902.22
B32: TOTAL LIABILITIES + EQUITY | C32: =Engine!D146 -> 2792981 | D32: =Engine!E146 -> 2833837.1 | E32: =Engine!F146 -> 2875539 | F32: =Engine!G146 -> 2918165.4
B33: Balance sheet check | C33: =Engine!D147 -> 0 | D33: =Engine!E147 -> 0 | E33: =Engine!F147 -> 0 | F33: =Engine!G147 -> 0
B35: PROFITABILITY (EUR millions)
C36: 2025A | D36: 2026F | E36: 2027F | F36: 2028F
B37: Net Interest Income | C37: =Model!C23 -> 22085.252 | D37: =Model!D23 -> 22685.669 | E37: =Model!E23 -> 23224.923 | F37: =Model!F23 -> 24295.945
B38: Fee income | C38: =Model!C24 -> 22343.848 | D38: =Model!D24 -> 22670.697 | E38: =Model!E24 -> 23004.312 | F38: =Model!F24 -> 23345.323
B39: Total Revenue | C39: =Model!C25 -> 44429.1 | D39: =Model!D25 -> 45356.365 | E39: =Model!E25 -> 46229.236 | F39: =Model!F25 -> 47641.269
B40: Operating Expenses | C40: =Model!C26 -> -27546.042 | D40: =Model!D26 -> -28120.946 | E40: =Model!E26 -> -28662.126 | F40: =Model!F26 -> -29537.586
B41: Provisions / CoR | C41: =Model!C28 -> -2243.395 | D41: =Model!D28 -> -2310.6968 | E41: =Model!E28 -> -2380.0178 | F41: =Model!F28 -> -2451.4183
B42: Net Income | C42: =Model!C31 -> 10979.747 | D42: =Model!D31 -> 11193.541 | E42: =Model!E31 -> 11390.319 | F42: =Model!F31 -> 11739.198
B44: NIM | C44: =Model!D132 -> 0.017318894 | D44: =Model!E132 -> 0.017379544 | E44: =Model!F132 -> 0.017329328 | F44: =Model!G132 -> 0.017657824
B45: ROE | C45: =Model!C34 -> 0.083071031 | D45: =Model!D34 -> 0.081913702 | E45: =Model!E34 -> 0.080664242 | F45: =Model!F34 -> 0.080459348
B46: Cost-to-Income | C46: =Model!C36 -> 0.62 | D46: =Model!D36 -> 0.62 | E46: =Model!E36 -> 0.62 | F46: =Model!F36 -> 0.62
B48: FUNDING & LIQUIDITY
C49: Threshold | D49: 2025A | E49: 2026F | F49: 2027F | G49: 2028F
B50: Loan-to-deposit ratio | C50: — | D50: =Engine!D149 -> 0.8343139 | E50: =Engine!E149 -> 0.83838373 | F50: =Engine!F149 -> 0.8424734 | G50: =Engine!G149 -> 0.84658303
B51: Stable funding / total | C51: — | D51: =Engine!D151 -> 0.43241862 | E51: =Engine!E151 -> 0.43725291 | F51: =Engine!F151 -> 0.44208093 | G51: =Engine!G151 -> 0.44691333
B52: LCR | C52: ≥ 100% | D52: =Model!D140 -> 1.5544069 | E52: =Model!E140 -> 1.5354828 | F52: =Model!F140 -> 1.5471072 | G52: =Model!G140 -> 1.5580125
B53: NSFR | C53: ≥ 1.00x | D53: =Model!D141 -> 1.0989131 | E53: =Model!E141 -> 1.0284199 | F53: =Model!F141 -> 1.0265263 | G53: =Model!G141 -> 1.024625
B55: RISK & REGULATORY
C56: Threshold | D56: 2025A | E56: 2026F | F56: 2027F | G56: 2028F
B57: CET1 ratio | C57: ≥ 13.5% | D57: =Model!D138 -> 0.15745595 | E57: =Model!E138 -> 0.15879656 | F57: =Model!F138 -> 0.16004729 | G57: =Model!G138 -> 0.16127587
B58: Leverage ratio | C58: ≥ 3.0% | D58: =Model!D139 -> 0.047323272 | E58: =Model!E139 -> 0.048220985 | F58: =Model!F139 -> 0.049106113 | G58: =Model!G139 -> 0.049997928
B59: LCR | C59: ≥ 100% | D59: =Model!D140 -> 1.5544069 | E59: =Model!E140 -> 1.5354828 | F59: =Model!F140 -> 1.5471072 | G59: =Model!G140 -> 1.5580125
B60: NSFR | C60: ≥ 1.00x | D60: =Model!D141 -> 1.0989131 | E60: =Model!E141 -> 1.0284199 | F60: =Model!F141 -> 1.0265263 | G60: =Model!G141 -> 1.024625
B62: IRRBB — Interest Rate Risk
B63: EVE / Tier 1 capital | D63: =Model!E229 -> 0.13246837
B64: Outlier status (>15% = breach) | D64: =IF(Model!E229>0.15,"BREACH — "&TEXT(Model!E229,"0.0%")&" > 15%","PASS") -> PASS
B65: NII sensitivity (+200bps / NII) | D65: =Model!C54 -> 0.34708374
B67: SCENARIO COMPARISON — 2026F
C68: Base | D68: Rate Hike | E68: Rate Cut | F68: Stress
B69: NII (€bn) | C69: =Model!C149/1000 -> 22.685669 | D69: =Model!D149/1000 -> 20.216592 | E69: =Model!E149/1000 -> 18.815639 | F69: =Model!F149/1000 -> 15.812502
B70: NIM | C70: =Model!C150 -> 0.017379544 | D70: =Model!D150 -> 0.015487979 | E70: =Model!E150 -> 0.014414705 | F70: =Model!F150 -> 0.012113994
B71: Net Income (€bn) | C71: =Model!C157/1000 -> 11.193541 | D71: =Model!D157/1000 -> 9.8215956 | E71: =Model!E157/1000 -> 10.748335 | F71: =Model!F157/1000 -> 5.9425852
B72: CET1 (scenario) | C72: =Engine!C251 -> 0.15879656 | D72: =Engine!C252 -> 0.15897644 | E72: =Engine!C253 -> 0.15777818 | F72: =Engine!C254 -> 0.16019043
B73: ="Validation: "&Model!E265&" | "&Model!E267&" | "&Model!E268 -> Validation: PASS | PASS | PASS
B74: ="Model "&Engine!C103&" | Last updated: "&TEXT(Engine!C111,"DD-MMM-YYYY")&" | Prepared by: "&Engine!F111 -> Model v1.0 | Last updated: 24-Mar-2026 | Prepared by: Hossam Eltarrass
B76: CHARTS
B122: Min. 13.5% | D122: 0.135 | E122: 0.135 | F122: 0.135 | G122: 0.135

Sheet Master Balance Sheet
B1: BNP PARIBAS — ALM Master Model | Master Balance Sheet | EUR millions
B2: Line Item | C2: 2024A | D2: 2025A
B3: ASSETS
B4: Cash and balances at central banks | C4: 182496 | D4: 211330
B5: Financial instruments FVTPL — trading | C5: 267357 | D5: 321293
B6: Financial instruments FVTPL — non-trading | C6: 225699 | D6: 254310
B7: Financial instruments FVTPL — designated | C7: 322631 | D7: 274625
B8: Derivatives used for hedging purposes (asset) | C8: 20851 | D8: 20017
B9: Financial assets FVOCI — Equity instruments WARNING: NOT HQLA — use MBS row 10 NOT row 9 | C9: 71430 | D9: 77940
B10: Financial assets FVOCI — Debt instruments ✓ HQLA eligible | C10: 1610 | D10: 1420
B11: Financial assets amortised cost — Loans to credit institutions | C11: 31147 | D11: 26259
B12: Financial assets amortised cost — Loans to customers | C12: 900141 | D12: 897358
B13: Financial assets amortised cost — Debt securities ✓ HQLA eligible | C13: 146975 | D13: 151687
B14: Remeasurement adjustment on interest-rate risk hedges | C14: -758 | D14: -2335
B15: Insurance investment assets WARNING: 100% RSF per CRR Art.428ab | C15: 286849 | D15: 305471
... B21: Goodwill | C21: 5550 | D21: 7133
B22: Assets held for sale | D22: 7805
B23: TOTAL ASSETS | C23: 2704908 | D23: 2792981
B24: LIABILITIES
B25: Deposits from central banks | C25: 3366 | D25: 4401
B26: Financial liabilities FVTPL — trading | C26: 79958 | D26: 98487
B27: Financial liabilities FVTPL — repo / structured | C27: 304817 | D27: 357947
B28: Financial liabilities FVTPL — other trading | C28: 104934 | D28: 129279
B29: Financial liabilities FVTPL — designated | C29: 301953 | D29: 252726
B30: Derivatives used for hedging purposes (liability) WARNING: EXCLUDE from IRRBB | C30: 36864 | D30: 28493
B31: Financial liabilities AC — Deposits from credit institutions | C31: 66872 | D31: 69938
B32: Financial liabilities AC — Customer deposits | C32: 1034857 | D32: 1075564
B33: Financial liabilities AC — Debt securities issued | C33: 198119 | D33: 173933
B34: Financial liabilities AC — Subordinated debt | C34: 31799 | D34: 34468
B35: Remeasurement adjustment on interest-rate risk hedges | C35: -10696 | D35: -9811
B36: Current and deferred tax liabilities | C36: 3657 | D36: 3336
... B40: Provisions for contingencies and charges | C40: 9806 | D40: 10193
B41: Liabilities associated with assets held for sale | D41: 6072
B42: TOTAL LIABILITIES | C42: 2570767 | D42: 2660808
B43: EQUITY
B44: Share capital, paid-in capital and retained earnings | C44: 118957 | D44: 117787
B45: Net income attributable to shareholders | C45: 11688 | D45: 12225
B46: Total capital, retained earnings and net income | C46: 130645 | D46: 130012
B47: Changes recognised in equity (AOCI) | C47: -2508 | D47: -4499
B48: Shareholders equity | C48: 128137 | D48: 125513
B49: Minority interests | C49: 6004 | D49: 6660
B50: TOTAL EQUITY | C50: 134141 | D50: 132173
B51: TOTAL LIABILITIES AND EQUITY | C51: 2704908 | D51: 2792981
B53: KEY: Red = excluded from HQLA or special regulatory treatment | Green = HQLA eligible | All figures in EUR millions

Sheet Engine
B1: BNP PARIBAS — ALM Engine | Assumptions & Balance Sheet Forecast
B2: SECTION A1 — SCENARIO CONTROL | H2: pr
B3: [Note] Cell C5 MUST have Data Validation → List → Source: 1,2,3,4 This ONE cell drives the entire model.
B4: Scenario ID (linked from Dashboard — do NOT edit here) | C4: =Dashboard!G4 -> 1
B5: Row 8 = LIVE SCENARIO (write CHOOSE formulas): | C5: =CHOOSE($C$4,C7,C8,C9,C10) -> 0 | D5: =CHOOSE($C$4,D7,D8,D9,D10) -> 0.03 | E5: =CHOOSE($C$4,E7,E8,E9,E10) -> 0.025 | F5: =CHOOSE($C$4,F7,F8,F9,F10) -> 0.4 | G5: =CHOOSE($C$4,G7,G8,G9,G10) -> 25 | H5: =CHOOSE($C$4,H7,H8,H9,H10) -> 0.62
C6: Rate Shock | D6: Loan Growth | E6: Dep Growth | F6: Dep Beta | G6: CoR bps | H6: CIR
B7: 1 — Base | C7: 0 | D7: 0.03 | E7: 0.025 | F7: 0.4 | G7: 25 | H7: 0.62
B8: 2 — Rate Hike | C8: 0.02 | D8: 0.02 | E8: 0.02 | F8: 0.5 | G8: 30 | H8: 0.63
B9: 3 — Rate Cut | C9: -0.02 | D9: 0.04 | E9: 0.03 | F9: 0.3 | G9: 20 | H9: 0.61
B10: 4 — Stress | C10: 0.03 | D10: 0.01 | E10: 0 | F10: 0.6 | G10: 60 | H10: 0.65
B12: SECTION A2 — MARKET RATE ENVIRONMENT | ECB / Bloomberg
B13: Parameter | C13: 2024A | D13: 2025A | E13: 2026F | F13: 2027F | G13: 2028F | H13: Source
B14: ECB Policy Rate (DFR) | C14: 0.04 | D14: 0.025 | E14: 0.0225 | F14: 0.02 | G14: 0.02 | H14: ECB press conf. 2025A=2.50% reached Sep-25
B15: 3M Euribor | C15: 0.039 | D15: 0.026 | E15: 0.0235 | F15: 0.021 | G15: 0.021 | H15: EMMI fixing avg. DFR+~10bps.
B16: 5Y Swap Rate | C16: 0.029 | D16: 0.028 | E16: 0.027 | F16: 0.026 | G16: 0.0255 | H16: Bloomberg EUR swap
B17: 10Y Swap Rate | C17: 0.027 | D17: 0.026 | E17: 0.0255 | F17: 0.025 | G17: 0.0245 | H17: Bloomberg EUR swap
B18: Δ ECB (formula) | D18: =D14-C14 -> -0.015 | E18: =E14-D14 -> -0.0025 | F18: =F14-E14 -> -0.0025 | G18: =G14-F14 -> 0
B19: Δ Euribor (formula) | D19: =D15-C15 -> -0.013 | E19: =E15-D15 -> -0.0025 | F19: =F15-E15 -> -0.0025 | G19: =G15-F15 -> 0
B21: SECTION A3 — SPREAD ASSUMPTIONS
B22: Spread Parameter | C22: 2024A | D22: 2025A | E22: 2026F | F22: 2027F | G22: 2028F | H22: Source
B23: Loan spread over 3M Euribor | C23: 0.012 | D23: 0.012 | E23: 0.012 | F23: 0.012 | G23: 0.012 | H23: BNP loan yield minus Euribor avg
B24: Loan repricing beta | C24: 0.9 | D24: 0.9 | E24: 0.9 | F24: 0.9 | G24: 0.9 | H24: 80% floating rate book
B25: Deposit spread below ECB | C25: -0.02 | D25: -0.02 | E25: -0.02 | F25: -0.02 | G25: -0.02 | H25: ECB minus ~200bps historically
B26: Bond portfolio yield spread | C26: 0.003 | D26: 0.004 | E26: 0.004 | F26: 0.004 | G26: 0.004 | H26: BNP FVOCI/AC over 10Y swap
B27: Interbank spread over Euribor | C27: 0.004 | D27: 0.005 | E27: 0.005 | F27: 0.005 | G27: 0.005 | H27: Money market unsecured
B28: Repo spread below ECB DFR | C28: -0.00085 | D28: -0.00085 | E28: -0.00085 | F28: -0.00085 | G28: -0.00085 | H28: ECB DFR minus ESTR ~8.5bps
B29: SU bond issuance spread over 10Y | C29: 0.0065 | D29: 0.0065 | E29: 0.0065 | F29: 0.0065 | G29: 0.0065 | H29: BNP SU credit spread ~65bps
B30: Sub debt blended cost (AT1+T2) | C30: 0.025 | D30: 0.025 | E30: 0.025 | F30: 0.025 | G30: 0.025 | H30: Blended AT1+T2 BNP Pillar 3
B32: SECTION A4 — BEHAVIOURAL PARAMETERS | EBA/GL/2022/14
B33: Parameter | C33: Value | H33: Regulatory Basis
B34: Retail deposit behavioural duration (yrs) | C34: 2.5 | H34: EBA/GL/2022/14 Table 2: 2-3Y effective duration
B35: Corporate deposit behavioural duration (yrs) | C35: 1 | H35: Basel IRRBB 2016 para 114: 1Y cap
B36: NMD core % (stable) | C36: 0.7 | H36: BCBS IRRBB 2016 para 114: up to 90%, use 70%
B37: NMD non-core % (overnight) | C37: 0.3 | H37: Residual = 100% minus core
B38: Securities: Gov bond % of portfolio | C38: 0.72 | H38: BNP 2025 HQLA ~72% sovereign
B39: Securities: Corp bond % of portfolio | C39: 0.28 | H39: Residual. Level 2A HQLA.
B40: Fee income ratio (% total assets) | C40: 0.008 | H40: BNP 2025 fees+commissions/total assets
B41: Dividend payout ratio | C41: 0.6 | H41: BNP stated policy: 60% payout
B43: SECTION A5 — IRRBB SHOCK PARAMETERS | EBA/GL/2022/14 ANNEX I
B44: Shock Scenario | C44: Shock | D44: Type | H44: Regulatory Source
B45: Parallel Up | C45: 200 | D45: Level | H45: EBA/GL/2022/14 Annex I Scenario 1 — mandatory outlier test
B46: Parallel Down | C46: -200 | D46: Level | H46: EBA/GL/2022/14 Annex I Scenario 2
B47: Steepener (+90/-90) | C47: 90 | D47: Curve | H47: EBA/GL/2022/14 Annex I Scenario 3
B48: Flattener (+90/-90) | C48: -90 | D48: Curve | H48: EBA/GL/2022/14 Annex I Scenario 4
B49: Short Rate Up | C49: 250 | D49: Short | H49: EBA/GL/2022/14 Annex I Scenario 5
B50: Short Rate Down | C50: -250 | D50: Short | H50: EBA/GL/2022/14 Annex I Scenario 6
B51: EVE Outlier Threshold | C51: 0.15 | D51: Limit | H51: CRR Art.448+EBA/GL/2022/14 para 114: >15% Tier1 = outlier
B52: NII Early Warning | C52: 0.05 | D52: Limit | H52: EBA/GL/2022/14 para 116: >5% NII triggers review
B54: SECTION A6 — LCR PARAMETERS | DEL. REG. (EU) 2022/786
B55: Parameter | C55: Value | H55: Article Reference
B56: Level 1 haircut: Cash+CB reserves | C56: 0 | H56: Art.10(1)(a): 0% haircut
B57: Level 1 haircut: Sovereign bonds | C57: 0 | H57: Art.10(1)(d-g): 0% haircut
B58: Level 2A haircut: IG corporate bonds | C58: 0.15 | H58: Art.11(1)(b): 15% minimum
B59: Level 2 cap (% of HQLA) | C59: 0.4 | H59: Art.17(1)(b): max 40%
B60: Level 2B cap (% of HQLA) | C60: 0.15 | H60: Art.17(1)(c): max 15% (use 0%)
B61: Outflow: Retail stable deposits | C61: 0.05 | H61: Art.24: 5%
B62: Outflow: Retail less stable | C62: 0.1 | H62: Art.25: 10%
B63: Outflow: Wholesale non-operational | C63: 0.25 | H63: Art.27(3): 25%
B64: Outflow: Financial institution unsecured | C64: 1 | H64: Art.31: 100%
B65: Outflow: Repo — Level 1 collateral | C65: 0 | H65: Art.28(3)(a): 0%
B66: Outflow: Repo — Level 2A collateral | C66: 0.15 | H66: Art.28(3)(b): 15%
B67: Outflow: Undrawn committed facilities | C67: 0.1 | H67: Art.32: 10%
... B71: Inflow cap (% of gross outflows) | C71: 0.75 | H71: Art.33: MANDATORY 75% cap
B73: SECTION A7 — NSFR PARAMETERS | CRR ART. 428a-428at
B74: Parameter | C74: Factor | H74: CRR Article
B75: EQUITY ASF: Equity (CET1+AT1+T2) | C75: 1 | H75: CRR Art.428d: 100%
B76: RETAIL ASF: Stable deposits | C76: 0.9 | H76: CRR Art.428h: 90%
B77: RETAIL ASF: Less stable deposits | C77: 0.8 | H77: CRR Art.428i: 80%
B78: WHOLESALE ASF: Bonds issued >1Y | C78: 1 | H78: CRR Art.428n: 100%
B79: WHOLESALE ASF: Bonds 6M-1Y | C79: 0.5 | H79: CRR Art.428o(2): 50%
B80: WHOLESALE ASF: Interbank <6M | C80: 0 | H80: CRR Art.428p: 0%
B81: WHOLESALE ASF: Repo Level 1 <6M | C81: 0.1 | H81: CRR Art.428q: 10%
B82: WHOLESALE ASF: Sub debt blended | C82: 0.5 | H82: Blended AT1+T2 conservative
B83: WHOLESALE ASF: CB deposits | C83: 0 | H83: CRR Art.428p: 0%
B84: RSF: Customer loans >1Y | C84: 0.85 | H84: CRR Art.428s(2): 85%
B85: RSF: Customer loans <1Y | C85: 0.5 | H85: CRR Art.428s(1): 50%
B86: RSF: HQLA Level 1 securities | C86: 0.05 | H86: CRR Art.428r: 5%
... B91: RSF: Other assets (PPE,goodwill) | C91: 1 | H91: CRR Art.428ab: 100%
B93: SECTION A8 — REGULATORY THRESHOLDS | CRR / CRDV
B94: Threshold | C94: Value | H94: Legal Basis
B95: CET1 minimum ratio | C95: 0.135 | H95: CRR Art.92: P1+Conservation+P2R+G-SII+CCyB = 13.5%
B96: AT1 minimum | C96: 0.015 | H96: CRR Art.92(1)(b): 1.5%
B97: Total Capital minimum | C97: 0.155 | H97: CRR Art.92(1)(c): 15.5%
B98: Leverage Ratio minimum | C98: 0.03 | H98: CRR Art.92(1)(d)+CRR2: 3.0%
B99: LCR minimum | C99: 1 | H99: Art.4 Del.Reg.(EU)2022/786: 100%
B100: NSFR minimum | C100: 1 | H100: CRR Art.428b (CRR2): 100%
B101: IRRBB EVE outlier | C101: 0.15 | H101: EBA/GL/2022/14 para 114: 15% Tier1
B102: IRRBB NII early warning | C102: 0.05 | H102: EBA/GL/2022/14 para 116: 5% NII
B103: Model Version | C103: v1.0
B104: SECTION A9 — MODEL CONTROLS
B105: Reporting Date | C105: 2025A
B106: Currency | C106: EUR
B107: Units | C107: EUR millions
B108: Institution | C108: BNP Paribas SA
B109: Regulatory Framework | C109: EU — Basel III / CRR2 / Del. Reg. (EU) 2022/786
B110: Forecast Horizon | C110: 3 Years (2026F–2028F)
B111: Last Updated | C111: 46105 | E111: Prepared By | F111: Hossam Eltarrass
B112: ZONE B — BALANCE SHEET FORECAST (Formula Cells — write formulas here, NOT yellow)
B113: [Note] ALL cells here are formula cells. Reference only: Zone A above OR Master Balance Sheet. NEVER hardcode a number. Balance sheet check row 147 MUST = 0 before moving to Model sheet.
B114: Item | C114: 2024A | D114: 2025A | E114: 2026F | F114: 2027F | G114: 2028F
...

Sheet Model
B1: BNP PARIBAS — ALM Model | Calculations | All figures EUR millions
B2: ="SECTION 1 — NII SIMULATION 2025A | Scenario: "&CHOOSE(Engine!C4,"Base","Rate Hike","Rate Cut","Stress") -> SECTION 1 — NII SIMULATION 2025A | Scenario: Base
B3: B — Asset / Liability | C3: Balance (€m) | D3: Rate | E3: Interest (€m)
B4: Cash & CB reserves (earns ECB DFR rate — NOT loan rate) | C4: =Engine!D126 -> 211330 | D4: =Engine!D14 -> 0.025 | E4: =C4*D4 -> 5283.25
B5: Loans to customers | C5: =Engine!D128 -> 897358 | D5: =Engine!D116 -> 0.038 | E5: =C5*D5 -> 34099.604
B6: Interbank loans | C6: =Engine!D129 -> 26259 | D6: =Engine!D121 -> 0.031 | E6: =C6*D6 -> 814.029
B7: Securities portfolio | C7: =Engine!D130 -> 153107 | D7: =Engine!D119 -> 0.03 | E7: =C7*D7 -> 4593.21
B8: Total Interest Income | C8: =SUM(C4:C7) -> 1288054 | E8: =SUM(E4:E7) -> 44790.093
B10: B — Liability | C10: Balance (€m) | D10: Rate | E10: Interest Cost (€m)
B11: Customer deposits | C11: =Engine!D136 -> 1075564 | D11: =Engine!D117 -> 0.005 | E11: =C11*D11 -> 5377.82
B12: Interbank funding | C12: =Engine!D137 -> 69938 | D12: =Engine!D121 -> 0.031 | E12: =C12*D12 -> 2168.078
B13: Repo funding | C13: =Engine!D138 -> 357947 | D13: =Engine!D118 -> 0.02415 | E13: =C13*D13 -> 8644.4201
B14: Bonds issued | C14: =Engine!D139 -> 173933 | D14: =Engine!D120 -> 0.0325 | E14: =C14*D14 -> 5652.8225
B15: Subordinated debt | C15: =Engine!D140 -> 34468 | D15: =Engine!D122 -> 0.025 | E15: =C15*D15 -> 861.7
B16: Total Interest Expense | C16: =SUM(C11:C15) -> 1711850 | E16: =SUM(E11:E15) -> 22704.841
B18: ★ NET INTEREST INCOME | C18: =E8-E16 -> 22085.252
B19: Average earning assets (see guide for formula) | C19: =(Engine!C126+Engine!C128+Engine!C129+Engine!C130+Engine!D126+Engine!D128+Engine!D129+Engine!D130)/2 -> 1275211.5
B20: NIM | C20: =C18/C19 -> 0.017318894
B21: ="SECTION 2 — P&L MODEL | 2025A→2028F | Scenario: "&CHOOSE(Engine!C4,"Base","Rate Hike","Rate Cut","Stress") -> SECTION 2 — P&L MODEL | 2025A→2028F | Scenario: Base
B22: B — P&L Line | C22: 2025A | D22: 2026F | E22: 2027F | F22: 2028F
B23: Net Interest Income | C23: =C18 -> 22085.252 | D23: =(Engine!E126*Engine!E14)+(Engine!E128*Engine!E116)+(Engine!E129*Engine!E121)+(Engine!E130*Engine!E119)-((Engine!E136*Engine!E117)+(Engine!E137*Engine!E121)+(Engine!E138*Engine!E118)+(Engine!E139*Engine!E120)+(Engine!E140*Engine!E122)) -> 22685.669 | E23: =(Engine!F126*Engine!F14)+(Engine!F128*Engine!F116)+(Engine!F129*Engine!F121)+(Engine!F130*Engine!F119)-((Engine!F136*Engine!F117)+(Engine!F137*Engine!F121)+(Engine!F138*Engine!F118)+(Engine!F139*Engine!F120)+(Engine!F140*Engine!F122)) -> 23224.923 | F23: =(Engine!G126*Engine!G14)+(Engine!G128*Engine!G116)+(Engine!G129*Engine!G121)+(Engine!G130*Engine!G119)-((Engine!G136*Engine!G117)+(Engine!G137*Engine!G121)+(Engine!G138*Engine!G118)+(Engine!G139*Engine!G120)+(Engine!G140*Engine!G122)) -> 24295.945
B24: Fee income | C24: =Engine!D132*Engine!$C$40 -> 22343.848 | D24: =Engine!E132*Engine!$C$40 -> 22670.697 | E24: =Engine!F132*Engine!$C$40 -> 23004.312 | F24: =Engine!G132*Engine!$C$40 -> 23345.323
B25: Total Revenue | C25: =C23+C24 -> 44429.1 | D25: =D23+D24 -> 45356.365 | E25: =E23+E24 -> 46229.236 | F25: =F23+F24 -> 47641.269
B26: Operating Expenses | C26: =C25*(-Engine!$H$5) -> -27546.042 | D26: =D25*(-Engine!$H$5) -> -28120.946 | E26: =E25*(-Engine!$H$5) -> -28662.126 | F26: =F25*(-Engine!$H$5) -> -29537.586
B27: Gross Operating Income | C27: =C25+C26 -> 16883.058 | D27: =D25+D26 -> 17235.419 | E27: =E25+E26 -> 17567.11 | F27: =F25+F26 -> 18103.682
B28: Provisions / CoR | C28: =-(Engine!D128*Engine!$G$5/10000) -> -2243.395 | D28: =-(Engine!E128*Engine!$G$5/10000) -> -2310.6968 | E28: =-(Engine!F128*Engine!$G$5/10000) -> -2380.0178 | F28: =-(Engine!G128*Engine!$G$5/10000) -> -2451.4183
B29: Pre-Tax Income | C29: =C27+C28 -> 14639.663 | D29: =D27+D28 -> 14924.722 | E29: =E27+E28 -> 15187.092 | F29: =F27+F28 -> 15652.264
B30: Income Tax (25%) | C30: =C29*(-Engine!$C$156) -> -3659.9158 | D30: =D29*(-Engine!$C$156) -> -3731.1805 | E30: =E29*(-Engine!$C$156) -> -3796.7729 | F30: =F29*(-Engine!$C$156) -> -3913.0659
B31: Net Income | C31: =C29+C30 -> 10979.747 | D31: =D29+D30 -> 11193.541 | E31: =E29+E30 -> 11390.319 | F31: =F29+F30 -> 11739.198
B32: Dividend (60% payout) | C32: =C31*(-Engine!$C$41) -> -6587.8484 | D32: =D31*(-Engine!$C$41) -> -6716.1249 | E32: =E31*(-Engine!$C$41) -> -6834.1913 | F32: =F31*(-Engine!$C$41) -> -7043.5187
B33: Retained Earnings | C33: =C31+C32 -> 4391.899 | D33: =D31+D32 -> 4477.4166 | E33: =E31+E32 -> 4556.1275 | F33: =F31+F32 -> 4695.6791
B34: ROE | C34: =C31/Engine!D145 -> 0.083071031 | D34: =D31/Engine!E145 -> 0.081913702 | E34: =E31/Engine!F145 -> 0.080664242 | F34: =F31/Engine!G145 -> 0.080459348
B35: ROA | C35: =C31/Engine!D132 -> 0.003931193 | D35: =D31/Engine!E132 -> 0.0039499594 | E35: =E31/Engine!F132 -> 0.0039611074 | F35: =F31/Engine!G132 -> 0.0040228007
B36: CIR check | C36: =(-C26)/C25 -> 0.62 | D36: =(-D26)/D25 -> 0.62 | E36: =(-E26)/E25 -> 0.62 | F36: =(-F26)/F25 -> 0.62
B38: ="SECTION 3 — REPRICING GAP 2025A | EBA/GL/2022/14 | Scenario: "&CHOOSE(Engine!C4,"Base","Rate Hike","Rate Cut","Stress") -> SECTION 3 — REPRICING GAP 2025A | EBA/GL/2022/14 | Scenario: Base
B39: B — Time Bucket | C39: Assets (€m) | D39: Liabilities (€m) | E39: GAP | F39: Cum. GAP | G39: ΔNii per 100bps
B40: Overnight | C40: =Engine!D126+Engine!D129*0.5 -> 224459.5 | D40: =Engine!D136*CHOOSE(Engine!C4,Engine!F7,Engine!F8,Engine!F9,Engine!F10) + Engine!D137*0.6 + Engine!D138 -> 830135.4 | E40: =C40-D40 -> -605675.9 | F40: =E40 -> -605675.9 | G40: =E40*Engine!$C$176*(1/365) -> -4.9781581
B41: 0–3 Months | C41: =Engine!D128*Engine!$C$160+Engine!D129*0.5+Engine!D130*0.05 -> 828407.05 | D41: =Engine!D136*Engine!$C$36*Engine!$C$168+Engine!D137*0.4 -> 103264.68 | E41: =C41-D41 -> 725142.37 | F41: =F40+E41 -> 119466.47 | G41: =E41*0.01*Engine!$C$177 -> 906.42796
B42: 3–6 Months | C42: =Engine!D128*Engine!$C$161+Engine!D130*0.05 -> 25602.51 | D42: =Engine!D136*Engine!$C$36*Engine!$C$169 -> 75289.48 | E42: =C42-D42 -> -49686.97 | F42: =F41+E42 -> 69779.5 | G42: =E42*0.01*Engine!$C$178 -> -186.32614
B43: 6–12 Months | C43: =Engine!D128*Engine!$C$162+Engine!D130*0.1 -> 42231.44 | D43: =Engine!D136*Engine!$C$36*Engine!$C$170 -> 112934.22 | E43: =C43-D43 -> -70702.78 | F43: =F42+E43 -> -923.28 | G43: =E43*0.01*Engine!$C$179 -> -530.27085
B44: 1–2 Years | C44: =Engine!D128*Engine!$C$163+Engine!D130*0.15 -> 40913.21 | D44: =Engine!D136*Engine!$C$36*Engine!$C$171+Engine!D139*0.1 -> 205617 | E44: =C44-D44 -> -164703.79 | F44: =F43+E44 -> -165627.07 | G44: =E44*0.01*Engine!$C$180 -> -2470.5568
B45: 2–5 Years | C45: =Engine!D128*Engine!$C$164+Engine!D130*0.35 -> 71534.61 | D45: =Engine!D136*Engine!$C$36*Engine!$C$172+Engine!D139*0.5 -> 312834.94 | E45: =C45-D45 -> -241300.33 | F45: =F44+E45 -> -406927.4 | G45: =E45*0.01*Engine!$C$181 -> -8445.5115
B46: 5+ Years | C46: =Engine!D128*Engine!$C$165+Engine!D130*0.3 -> 54905.68 | D46: =Engine!D136*Engine!$C$36*Engine!$C$173+Engine!D139*0.4+Engine!D140 -> 179330.68 | E46: =C46-D46 -> -124425 | F46: =F45+E46 -> -531352.4 | G46: =E46*0.01*Engine!$C$182 -> -8709.75
B47: Total/Check | C47: =SUM(C40:C46) -> 1288054 | D47: =SUM(D40:D46) -> 1819406.4 | E47: =SUM(E40:E46) -> -531352.4 | F47: =F46 -> -531352.4 | G47: =SUM(G40:G46) -> -19440.966
B48: Asset Check | C48: =C47-(Engine!D126+Engine!D128+Engine!D129+Engine!D130) -> 0 | D48: =D47-(Engine!D136+Engine!D137+Engine!D138+Engine!D139+Engine!D140) -> 107556.4
B49: ="SECTION 4 — IRRBB | EBA/GL/2022/14 | HEDGING DERIVATIVES EXCLUDED | Scenario: "&CHOOSE(Engine!C4,"Base","Rate Hike","Rate Cut","Stress") -> SECTION 4 — IRRBB | EBA/GL/2022/14 | HEDGING DERIVATIVES EXCLUDED | Scenario: Base
B50: B — Item | C50: NII View (12M) | D50: EVE View (Full BS)
B51: Rate-sensitive assets | C51: =Engine!D126+Engine!D128*Engine!$C$24+Engine!D130 -> 1172059.2 | D51: =Engine!D128+Engine!D129+Engine!D130+Engine!D126 -> 1288054
B52: Rate-sensitive liabilities | C52: =Engine!D138+Engine!D137+Engine!D136*(1-Engine!$C$36)+Engine!D139*0.2+Engine!D140*0.1 -> 788787.6 | D52: =Engine!D136+Engine!D137+Engine!D138+Engine!D139+Engine!D140 -> 1711850
B53: IRRBB GAP | C53: =C51-C52 -> 383271.6 | D53: =D51-D52 -> -423796
B54: Regulatory Metrics | C54: =ABS(C57)/C18 -> 0.34708374 | D54: =MAX(ABS(D57),ABS(D58),ABS(D59),ABS(D60),ABS(D61),ABS(D62))/Engine!D145 -> 0.13246837
B55: Total PVBP (€m per 1bp) | C55: — | D55: =(E40*Engine!$C$176)+(E41*Engine!$C$177)+(E42*Engine!$C$178)+(E43*Engine!$C$179)+(E44*Engine!$C$180)+(E45*Engine!$C$181)+(E46*Engine!$C$182) -> -1945415.8
B56: B — Shock Scenario | C56: NII Impact (€m) | D56: EVE Impact (€m)
B57: Parallel Up +200bps | C57: =C53*Engine!$C$45/10000 -> 7665.432 | D57: =D55*Engine!$C$45/10000*(1-Engine!$C$256) -> -17508.742
B58: Parallel Down -200bps | C58: =C53*Engine!$C$46/10000*Engine!$C$184 -> -6515.6172 | D58: =D55*ABS(Engine!$C$46)/10000*(-Engine!$C$184)*(1-Engine!$C$256) -> 14882.431
B59: Steepener | C59: =C53*Engine!$C$47/10000 -> 3449.4444 | D59: =((E44*Engine!$C$180+E45*Engine!$C$181+E46*Engine!$C$182)-(E40*Engine!$C$176+E41*Engine!$C$177+E42*Engine!$C$178+E43*Engine!$C$179))*Engine!$C$47/10000*(1-Engine!$C$256) -> -8017.979
B60: Flattener | C60: =C53*Engine!$C$48/10000 -> -3449.4444 | D60: =((E40*Engine!$C$176+E41*Engine!$C$177+E42*Engine!$C$178+E43*Engine!$C$179)-(E44*Engine!$C$180+E45*Engine!$C$181+E46*Engine!$C$182))*ABS(Engine!$C$48)/10000*(1-Engine!$C$256) -> 8017.979
B61: Short Rate Up | C61: =C53*Engine!$C$49/10000 -> 9581.79 | D61: =(E40*Engine!$C$176+E41*Engine!$C$177+E42*Engine!$C$178+E43*Engine!$C$179)*Engine!$C$49/10000*(1-Engine!$C$256) -> 193.11829
B62: Short Rate Down | C62: =C53*Engine!$C$50/10000*Engine!$C$184 -> -8144.5215 | D62: =(E40*Engine!$C$176+E41*Engine!$C$177+E42*Engine!$C$178+E43*Engine!$C$179)*ABS(Engine!$C$50)/10000*(-Engine!$C$184)*(1-Engine!$C$256) -> -164.15054
B63: =IF(MAX(ABS(D57),ABS(D58),ABS(D59),ABS(D60),ABS(D61),ABS(D62))/Engine!D145>Engine!C51,"⛔ EVE OUTLIER: "&TEXT(MAX(ABS(D57),ABS(D58),ABS(D59),ABS(D60),ABS(D61),ABS(D62))/Engine!D145,"0.0%")&" > 15%","EVE OK: "&TEXT(MAX(ABS(D57),ABS(D58),ABS(D59),ABS(D60),ABS(D61),ABS(D62))/Engine!D145,"0.0%")) -> EVE OK: 13.2%
B64: =IF(ABS(C57)/C18>Engine!C52,"NII sensitivity >"&TEXT(Engine!C52,"0%")&": "&TEXT(ABS(C57)/C18,"0.0%"),"NII OK: "&TEXT(ABS(C57)/C18,"0.0%")) -> NII sensitivity >5%: 34.7%
B65: Worst EVE Scenario | C65: =IF(ABS(D57)=D65,B57,IF(ABS(D58)=D65,B58,IF(ABS(D59)=D65,B59,IF(ABS(D60)=D65,B60,IF(ABS(D61)=D65,B61,B62))))) -> Parallel Up +200bps | D65: =MAX(ABS(D57),ABS(D58),ABS(D59),ABS(D60),ABS(D61),ABS(D62)) -> 17508.742 | E65: €m — absolute worst EVE impact
B66: Worst NII Scenario | C66: =IF(ABS(C57)=D66,B57,IF(ABS(C58)=D66,B58,IF(ABS(C59)=D66,B59,IF(ABS(C60)=D66,B60,IF(ABS(C61)=D66,B61,B62))))) -> Short Rate Up | D66: =MAX(ABS(C57),ABS(C58),ABS(C59),ABS(C60),ABS(C61),ABS(C62)) -> 9581.79 | E66: €m — absolute worst NII impact
B68: SECTION 5 — LCR | DELEGATED REGULATION (EU) 2022/786
B69: B — Item | C69: Amount (€m) | D69: 2026F | E69: 2027F | F69: 2028F
B70: Level 1: Cash & CB reserves | C70: =Engine!D126 -> 211330 | D70: =Engine!E126*(1-Engine!$C$56) -> 214325.33 | E70: =Engine!F126*(1-Engine!$C$56) -> 217157.6 | F70: =Engine!G126*(1-Engine!$C$56) -> 219876.42
B71: Level 1: Government bonds | C71: =Engine!D130*Engine!C38 -> 110237.04 | D71: =Engine!E130*Engine!$C$38*(1-Engine!$C$57) -> 113544.15 | E71: =Engine!F130*Engine!$C$38*(1-Engine!$C$57) -> 116950.48 | F71: =Engine!G130*Engine!$C$38*(1-Engine!$C$57) -> 120458.99
B72: Level 2A: Corporate bonds | C72: =Engine!D130*Engine!C39 -> 42869.96 | D72: =Engine!E130*Engine!$C$39*(1-Engine!$C$58) -> 37532.65 | E72: =Engine!F130*Engine!$C$39*(1-Engine!$C$58) -> 38658.629 | F72: =Engine!G130*Engine!$C$39*(1-Engine!$C$58) -> 39818.388
B73: FVOCI equity | C73: =0 -> 0 | D73: =0 -> 0 | E73: =0 -> 0 | F73: =0 -> 0
B74: TOTAL HQLA | C74: =SUM(C70:C73) -> 364437 | D74: =SUM(D70:D73) -> 365402.13 | E74: =SUM(E70:E73) -> 372766.71 | F74: =SUM(F70:F73) -> 380153.8
B76: 30-Day Outflows
B77: Retail deposits — stable | C77: =Engine!D136*0.7*Engine!C61 -> 37644.74 | D77: =Engine!E136*0.7*Engine!$C$61 -> 38585.859 | E77: =Engine!F136*0.7*Engine!$C$61 -> 39550.505 | F77: =Engine!G136*0.7*Engine!$C$61 -> 40539.268
B78: Retail deposits — less stable | C78: =Engine!D136*0.3*Engine!C62 -> 32266.92 | D78: =Engine!E136*0.3*Engine!$C$62 -> 33073.593 | E78: =Engine!F136*0.3*Engine!$C$62 -> 33900.433 | F78: =Engine!G136*0.3*Engine!$C$62 -> 34747.944
B79: Wholesale non-operational | C79: =Engine!D139*Engine!C63 -> 43483.25 | D79: =Engine!E139*Engine!$C$63 -> 43483.25 | E79: =Engine!F139*Engine!$C$63 -> 43483.25 | F79: =Engine!G139*Engine!$C$63 -> 43483.25
B80: Interbank (fin. inst.) | C80: =Engine!D137*Engine!C64 -> 69938 | D80: =Engine!E137*Engine!$C$64 -> 69938 | E80: =Engine!F137*Engine!$C$64 -> 69938 | F80: =Engine!G137*Engine!$C$64 -> 69938
B81: Repo — Level 1 collateral | C81: =Engine!D138*Engine!C38*Engine!C65 -> 0 | D81: =Engine!E138*Engine!$C$38*Engine!$C$65 -> 0 | E81: =Engine!F138*Engine!$C$38*Engine!$C$65 -> 0 | F81: =Engine!G138*Engine!$C$38*Engine!$C$65 -> 0
B82: Repo — Level 2A collateral | C82: =Engine!D138*Engine!C39*Engine!C66 -> 15033.774 | D82: =Engine!E138*Engine!$C$39*Engine!$C$66 -> 15033.774 | E82: =Engine!F138*Engine!$C$39*Engine!$C$66 -> 15033.774 | F82: =Engine!G138*Engine!$C$39*Engine!$C$66 -> 15033.774
B83: CB deposits (excess reserves) | C83: =Engine!D126*Engine!$C$186*Engine!$C$68 -> 7924.875 | D83: =Engine!E126*0.15*Engine!$C$68 -> 8037.1997 | E83: =Engine!F126*0.15*Engine!$C$68 -> 8143.41 | F83: =Engine!G126*0.15*Engine!$C$68 -> 8245.3658
B84: Undrawn commitments to corporates | C84: =Engine!D128*Engine!C67 -> 89735.8 | D84: =Engine!E128*Engine!$C$67 -> 92427.874 | E84: =Engine!F128*Engine!$C$67 -> 95200.71 | F84: =Engine!G128*Engine!$C$67 -> 98056.732
B85: Total Outflows (C90: =SUM(C82:C89)) | C85: =SUM(C77:C84) -> 296027.36 | D85: =SUM(D77:D84) -> 300579.55 | E85: =SUM(E77:E84) -> 305250.08 | F85: =SUM(F77:F84) -> 310044.33
B87: 30-Day Inflows + LCR Ratio
B88: Loan inflows | C88: =Engine!D128*0.1*Engine!C69 -> 44867.9 | D88: =Engine!E128*0.1*Engine!$C$69 -> 46213.937 | E88: =Engine!F128*0.1*Engine!$C$69 -> 47600.355 | F88: =Engine!G128*0.1*Engine!$C$69 -> 49028.366
B89: Securities inflows | C89: =(E70+E71)*0.05*Engine!C70 -> 16705.404 | D89: =(D70+D71)*0.05*Engine!$C$70 -> 16393.474 | E89: =(E70+E71)*0.05*Engine!$C$70 -> 16705.404 | F89: =(F70+F71)*0.05*Engine!$C$70 -> 17016.771
B90: Total Inflows (C95: =SUM(C93:C94)) | C90: =SUM(C88:C89) -> 61573.304 | D90: =SUM(D88:D89) -> 62607.411 | E90: =SUM(E88:E89) -> 64305.759 | F90: =SUM(F88:F89) -> 66045.136
B91: Inflow cap 75% | C91: =MIN(C90,C85*Engine!C71) -> 61573.304 | D91: =MIN(D90,D85*Engine!$C$71) -> 62607.411 | E91: =MIN(E90,E85*Engine!$C$71) -> 64305.759 | F91: =MIN(F90,F85*Engine!$C$71) -> 66045.136
B92: Net Outflows | C92: =C85-C91 -> 234454.06 | D92: =D85-D91 -> 237972.14 | E92: =E85-E91 -> 240944.32 | F92: =F85-F91 -> 243999.2
B93: ★ LCR RATIO | C93: =C74/C92 -> 1.5544069 | D93: =D74/D92 -> 1.5354828 | E93: =E74/E92 -> 1.5471072 | F93: =F74/F92 -> 1.5580125
B96: SECTION 6 — NSFR | CRR ART. 428a-428at
B97: [Note] ASF and RSF per CRR Art.428a-428at. Trading assets RSF (50% blended, Engine!C261) added to Total RSF. Insurance assets at 100% RSF per CRR Art.428ab.
B98: Available Stable Funding (ASF) | C98: 2025A | E98: 2026F | G98: 2027F | I98: 2028F
B99: Equity (100% ASF) | C99: =Engine!D145 -> 132173 | D99: =C99*Engine!C75 -> 132173 | E99: =Engine!E145 -> 136650.42 | F99: =E99*Engine!$C$75 -> 136650.42 | G99: =Engine!F145 -> 141206.54 | H99: =G99*Engine!$C$75 -> 141206.54 | I99: =Engine!G145 -> 145902.22 | J99: =I99*Engine!$C$75 -> 145902.22
B100: Retail deposits — stable (90%) | C100: =Engine!D136*0.7 -> 752894.8 | D100: =C100*Engine!C76 -> 677605.32 | E100: =Engine!E136*0.7 -> 771717.17 | F100: =E100*Engine!$C$76 -> 694545.45 | G100: =Engine!F136*0.7 -> 791010.1 | H100: =G100*Engine!$C$76 -> 711909.09 | I100: =Engine!G136*0.7 -> 810785.35 | J100: =I100*Engine!$C$76 -> 729706.82
B101: Retail deposits — less stable (80%) | C101: =Engine!D136*0.3 -> 322669.2 | D101: =C101*Engine!C77 -> 258135.36 | E101: =Engine!E136*0.3 -> 330735.93 | F101: =E101*Engine!$C$77 -> 264588.74 | G101: =Engine!F136*0.3 -> 339004.33 | H101: =G101*Engine!$C$77 -> 271203.46 | I101: =Engine!G136*0.3 -> 347479.44 | J101: =I101*Engine!$C$77 -> 277983.55
B102: Bonds issued (50%) | C102: =Engine!D139 -> 173933 | D102: =C102*Engine!C78 -> 173933 | E102: =Engine!E139 -> 173933 | F102: =E102*Engine!$C$78 -> 173933 | G102: =Engine!F139 -> 173933 | H102: =G102*Engine!$C$78 -> 173933 | I102: =Engine!G139 -> 173933 | J102: =I102*Engine!$C$78 -> 173933
B103: Sub debt blended (50%) | C103: =Engine!D140 -> 34468 | D103: =C103*Engine!C82 -> 17234 | E103: =Engine!E140 -> 34468 | F103: =E103*Engine!$C$82 -> 17234 | G103: =Engine!F140 -> 34468 | H103: =G103*Engine!$C$82 -> 17234 | I103: =Engine!G140 -> 34468 | J103: =I103*Engine!$C$82 -> 17234
B104: Interbank < 6M (0%) | C104: =Engine!D137 -> 69938 | D104: =C104*Engine!C80 -> 0 | E104: =Engine!E137 -> 69938 | F104: =E104*Engine!$C$80 -> 0 | G104: =Engine!F137 -> 69938 | H104: =G104*Engine!$C$80 -> 0 | I104: =Engine!G137 -> 69938 | J104: =I104*Engine!$C$80 -> 0
B105: Repo — Level 1 (10%) | C105: =Engine!D138 -> 357947 | D105: =C105*Engine!C81 -> 35794.7 | E105: =Engine!E138 -> 357947 | F105: =E105*Engine!$C$81 -> 35794.7 | G105: =Engine!F138 -> 357947 | H105: =G105*Engine!$C$81 -> 35794.7 | I105: =Engine!G138 -> 357947 | J105: =I105*Engine!$C$81 -> 35794.7
B106: CB deposits (0%) | C106: ='Master Balance Sheet'!D25 -> 4401 | D106: =C106*Engine!C83 -> 0 | E106: ='Master Balance Sheet'!D25 -> 4401 | F106: =E106*Engine!$C$83 -> 0 | G106: ='Master Balance Sheet'!D25 -> 4401 | H106: =G106*Engine!$C$83 -> 0 | I106: ='Master Balance Sheet'!D25 -> 4401 | J106: =I106*Engine!$C$83 -> 0
B107: Total ASF | C107: =SUM(C99:C106) -> 1848424 | D107: =SUM(D99:D106) -> 1294875.4 | F107: =SUM(F99:F106) -> 1322746.3 | H107: =SUM(H99:H106) -> 1351280.8 | J107: =SUM(J99:J106) -> 1380554.3
B109: Required Stable Funding (RSF) | C109: 2025A | E109: 2026F | G109: 2027F | I109: 2028F
...
